textanalyzer/__init__.py
textanalyzer/__main__.py
textanalyzer/analyzer.py
textanalyzerlib-0.1.0.dist-info/licenses/LICENSE
textanalyzerlib-0.1.0.dist-info/METADATA
textanalyzerlib-0.1.0.dist-info/WHEEL
textanalyzerlib-0.1.0.dist-info/entry_points.txt
textanalyzerlib-0.1.0.dist-info/top_level.txt
textanalyzerlib-0.1.0.dist-info/RECORD
