Metadata-Version: 2.4
Name: TextAnalyzerLib
Version: 0.1.0
Summary: Analyze text: words, sentences, characters, word frequency
Author: aisha aljmal
Author-email: aisha aljmal <moaljml3601@gmail.com>
License: MIT License
Project-URL: Homepage, https://pypi.org/project/TextAnalyzerLib/
Requires-Python: >=3.13
License-File: LICENSE
Dynamic: author
Dynamic: license-file
Dynamic: requires-python
